{
    "407116032042467339": {
        "exp": 0,
        "lvl": 1,
        "spam_count": 0,
        "warn": 0,
        "last_msg": 20200331132126,
        "last_spam": 1585628509,
        "kick_count": 1
    },
    "609010014111268894": {
        "exp": 40,
        "lvl": 1,
        "spam_count": 2,
        "warn": 1,
        "last_msg": 20200402224218,
        "last_spam": 1585834945,
        "kick_count": 0
    },
    "288302173912170497": {
        "exp": 0,
        "lvl": 1,
        "spam_count": 2,
        "warn": 0,
        "last_msg": 20200414085236,
        "last_spam": 1586854356,
        "kick_count": 0
    }
}